{
    "root": true,
    "title": "Ketuju Creative",
    "description": "Digital Creative Solutions",
    "icon": "SquareTerminal",
    "pages": [
        "---Layanan Umum---",
        "cara-kerja-dengan-kami",
        "pembayaran-dan-penagihan",
        "dukungan-pasca-proyek",
        "faq-umum",
        "---Pengembangan Website---",
        "jenis-website",
        "teknologi-platform",
        "proses-pengembangan-website",
        "panduan-pengelolaan-website",
        "---Pengembangan Aplikasi Mobile---",
        "jenis-aplikasi-mobile",
        "proses-pengembangan-aplikasi-mobile",
        "publikasi-aplikasi",
        "pemeliharaan-update-aplikasi",
        "---Desain & UI/UX---",
        "jenis-layanan-desain",
        "proses-desain-ui-ux",
        "deliverables-desain",
        "revisi-umpan-balik",
        "---IT Support---",
        "paket-it-support",
        "cara-mengajukan-tiket-support",
        "remote-support",
        "maintaince-rutin",
        "---Kebijakan & Keamanan---",
        "kebijakan-privasi-data",
        "keamanan",
        "syarat-dan-ketentuan",
        "penghentian-layanan"
    ]
}